bcvContext/__init__.py
bcvContext/bcvContext.py
bcvcontext-0.1.12.dist-info/METADATA
bcvcontext-0.1.12.dist-info/WHEEL
bcvcontext-0.1.12.dist-info/licenses/LICENSE
bcvcontext-0.1.12.dist-info/RECORD
