Metadata-Version: 2.1
Name: bcvContext
Version: 0.1.12
Summary: A small package to handle context path for the BCV generic workflow
Author-email: CEA <thomas.marques@cea.fr>
License-File: LICENSE
Classifier: License :: OSI Approved :: MIT License
Classifier: Operating System :: OS Independent
Classifier: Programming Language :: Python :: 3
Requires-Python: >=3.7
